[
  {
    "slug": "enhance-your-images-with-ai-upscaler-the-complete-local-super-resolution-guide",
    "title": "Enhance Your Images with AI Upscaler: The Complete Local Super-Resolution Guide",
    "category": "Tutorial",
    "date": "2026-07-24",
    "display_date": "July 24, 2026",
    "excerpt": "Enhance Your Images with AI Upscaler: The Complete Local Super-Resolution Guide\n\nWe've all been there—you find the perfect image for your project, on...",
    "url": "blog/posts/enhance-your-images-with-ai-upscaler-the-complete-local-super-resolution-guide.html"
  },
  {
    "slug": "how-to-remove-image-backgrounds-locally-with-cloakimg-ai-the-complete-guide",
    "title": "How to Remove Image Backgrounds Locally with CloakImg AI: The Complete Guide",
    "category": "Tutorial",
    "date": "2026-07-23",
    "display_date": "July 23, 2026",
    "excerpt": "How to Remove Image Backgrounds Locally with CloakImg AI: The Complete Guide\n\nRemoving the background from an image is one of the most common yet ted...",
    "url": "blog/posts/how-to-remove-image-backgrounds-locally-with-cloakimg-ai-the-complete-guide.html"
  }
]